streamlit/__init__.py
streamlit/a.py
Ammu123-0.1.dist-info/METADATA
Ammu123-0.1.dist-info/WHEEL
Ammu123-0.1.dist-info/entry_points.txt
Ammu123-0.1.dist-info/top_level.txt
Ammu123-0.1.dist-info/RECORD
