Metadata-Version: 2.1
Name: Ammu123
Version: 0.1
Requires-Dist: streamlit
